{
  "paivitetty": "2026-07-13T10:00:32.612915",
  "ravintolat": [
    {
      "nimi": "Lasihelmi",
      "url": "https://www.compass-group.fi/ravintolat-ja-ruokalistat/foodco/kaupungit/helsinki/lasihelmi/",
      "auki": "10:30–13:00",
      "hinta": "13,00 €",
      "paiva": "13.7.2026",
      "ruoat": [
        "Kesälomaa vietämme 6.7-2.8.2026 välisen ajan."
      ],
      "virhe": null
    },
    {
      "nimi": "Ravintola Fero",
      "url": "https://ravintolapalvelut.iss.fi/fero/",
      "auki": "10:30–13:30",
      "hinta": "13,40 €",
      "paiva": "13.7.2026",
      "ruoat": [
        "Ravintola Fero on kesätauolla 6.7-2.8 välisenä aikana."
      ],
      "virhe": null
    },
    {
      "nimi": "Ravintola Fucina",
      "url": "https://ravintolapalvelut.iss.fi/ravintola-fucina/",
      "auki": "10:30–13:30",
      "hinta": "13,90 €",
      "paiva": "13.7.2026",
      "ruoat": [
        "Keitto: Pesto-vuohenjuustokeittoa",
        "Lounas: Talon riistapullat tummalla rosmariinikastikkeella ja paneroidut kanaleikkeet",
        "Lounas: Paahdettua perunaa",
        "Lounas: Caponataa (Kasvismuhennos)",
        "Lounas: Kasvisvaihtoehto",
        "Lounas: Välimeren-kasvislasagnette",
        "Lounas: Pizza",
        "Lounas: Pizza Margherita & Pizza Pollo",
        "Jälkiruoka: Suklaamousse"
      ],
      "virhe": null
    },
    {
      "nimi": "Factory Pitäjänmäki",
      "url": "https://ravintolafactory.com/lounasravintolat/ravintolat/helsinki-pitajanmaki/",
      "auki": "10:00–14:00",
      "hinta": "13,20 €",
      "paiva": "13.7.2026",
      "ruoat": [
        "Palsternakka-basilikasosekeitto",
        "Chimichurri-paahdettua lohta (M+G+VS) paistetut varhaisperunat (VE+G) ruohosipuli-kermaviili",
        "Texmex lasagne cheddarjuustolla (VL+VS) parmesan muru",
        "Mausteinen biryani grillatuilla kasviksilla ja kanan siivillä",
        "Bataatti-kukkakaalicurry kauraproteiinisuikaleilla ja kormakastikkeella",
        "Cappuccinokakku"
      ],
      "virhe": null
    },
    {
      "nimi": "Ravintola Valaja",
      "url": "https://www.sodexo.fi/ravintolat/ravintola-valaja",
      "auki": "10:30–13:00",
      "hinta": "14,00 €",
      "paiva": "13.7.2026",
      "ruoat": [
        "Buffet: Ravintola on kiinni 6.7 - 2.8. Tervetuloa jälleen 3.8."
      ],
      "virhe": null
    },
    {
      "nimi": "Talin Kartano",
      "url": "https://www.ravintolatali.fi/lounas",
      "auki": "11:00–14:00",
      "hinta": "15,00 €",
      "paiva": "13.7.2026",
      "ruoat": [
        "(Ruokalista julkaistaan kuvana – katso ravintolan sivu)"
      ],
      "virhe": null,
      "kuvalista": true
    }
  ]
}